gylm-0.0.1.dist-info/METADATA
gylm-0.0.1.dist-info/WHEEL
gylm-0.0.1.dist-info/LICENSE
gylm-0.0.1.dist-info/top_level.txt
gylm-0.0.1.dist-info/RECORD
gylm/jaxfun.py
gylm/gnlylm.py
gylm/logger.py
gylm/readwrite.py
gylm/_gylm.cpython-39-x86_64-linux-gnu.so
gylm/soapgto.py
gylm/transformations.py
gylm/connectivity.py
gylm/__init__.py
gylm/ptable.py
gylm/cxx/ylm.cpp
gylm/cxx/celllist.cpp
gylm/cxx/bindings.cpp
gylm/cxx/soapgto.cpp
gylm/cxx/gylm.cpp
gylm/cxx/kernel.cpp
